Workbook

Sheet ABB (2)
A1: 宁波海越电器制造有限公司
A2: 产 品 报 价 单
A4: 项目名称：南岸服务区电力改造工程
A5: 产品名称：配电设备 电话： 报价单号：HY2601-0029
A6: 产品型号： 传真： 联系人：
A7: 序号 | B7: 名 称 | C7: 型 号 | D7: 单位 | E7: 数量 | F7: 单价(元) | G7: 金额(元)
A8: 1 | B8: 低压出线柜3D4 3D5 4D3 4D4 4D6 4D7 5D4 5D5 6D3 6D4 6D6 6D7 | C8: GCS | D8: 台 | E8: 12 | F8: =ROUND(H8,0) -> 39861 | G8: =E8*F8 -> 478332 | H8: =F55 -> 39861
A9: 2
A10: 3
A11: 4
A12: 5
A13: 6
A14: 7
A15: 8
A16: 9
A17: 10
A18: 合计 | B18: =G18 -> 478332 | G18: =SUM(G8:G17) -> 478332 | H18: 2155028 | N18: =H18/G18 -> 4.5052976 | O18: =G18*1.2 -> 573998.4 | P18: =H18*0.73 -> 1573170.4 | Q18: =P18/G18 -> 3.2888672 | R18: =G18/H18 -> 0.22196092
A19: 报价备注 | B19: 1、以上报价含13%增值税，含运费； | H19: =#REF!-G18 -> #REF!
B20: 2、气体绝缘环网柜采用施耐德公司产品；
B21: 3、高压真空断路器、低压断路器均采用ABB公司产品；
B22: 4、微机保护装置、数显仪表均采用宁波美格电力自动化工程有限公司产品；
B23: 5、电容电抗器采用台州安耐杰电力设备有限公司产品；
B24: 6、所有电器连接均采用含铜99.9%的纯铜连接；
B25: 7、产品质量免费保修壹年，终身服务。
A26: 报价日期：2026年1月28日 有效期：30天 报价：洪辉 审核:袁剑幸
A28: 地址：宁波市镇海骆驼机电园区盛兴路348号
A29: 电话：0574-86595601、86595616
A30: 传真：0574-86595600 联系人:陆建德 13884410385
A31: E-mail：info@nbhaiyue.com
A32: 宁波海越电器制造有限公司
A33: 报 价 明 细 表
A35: =B8 -> 低压出线柜3D4 3D5 4D3 4D4 4D6 4D7 5D4 5D5 6D3 6D4 6D6 6D7
A36: 序号 | B36: 名 称 | C36: 型 号 | D36: 数量(只) | E36: 单价(元) | F36: 金额(元) | G36: 产地/品牌 | I36: 电流 | J36: 总电缆费用 | K36: 柜宽 | L36: 电流 | M36: 铜排规格
A37: 1 | B37: 塑壳断路器 | C37: XT1N160 TMD 63 3P FF | D37: 0 | E37: =ROUND(H37,0) -> 444 | F37: =E37*D37 -> 0 | G37: =VLOOKUP(C37,库!A:D,4,FALSE()) -> ABB | H37: =VLOOKUP(C37,库!A:D,3,FALSE()) -> 443.754 | I37: =63*D37 -> 0 | J37: =80*D37*((K39/105-1)/2+1) -> 0 | K37: 0.8 | L37: 500 | M37: 0.18 | N37: =D37*166 -> 0 | O37: =400*D37 -> 0 | P37: =IF(F37<10000,F37*0.3,IF(F37>49999.99,F37*0.1,(0.29-0.000003125*F37)*F37)) -> 0
A38: 2 | B38: 塑壳断路器 | C38: XT1N160 TMD 100 3P FF | D38: 1 | E38: =ROUND(H38,0) -> 444 | F38: =E38*D38 -> 444 | G38: =VLOOKUP(C38,库!A:D,4,FALSE()) -> ABB | H38: =VLOOKUP(C38,库!A:D,3,FALSE()) -> 443.754 | I38: =100*D38 -> 100 | J38: =120*D38*((K39/105-1)/2+1) -> 117.14286 | K38: 铜价 | L38: 755 | M38: 0.24 | N38: =D38*166 -> 166 | O38: =400*D38 -> 400 | P38: =IF(F38<10000,F38*0.3,IF(F38>49999.99,F38*0.1,(0.29-0.000003125*F38)*F38)) -> 133.2
A39: 3 | B39: 塑壳断路器 | C39: XT1N160 TMD 160 3P FF | D39: 2 | E39: =ROUND(H39,0) -> 737 | F39: =E39*D39 -> 1474 | G39: =VLOOKUP(C39,库!A:D,4,FALSE()) -> ABB | H39: =VLOOKUP(C39,库!A:D,3,FALSE()) -> 736.794 | I39: =160*D39 -> 320 | J39: =120*D39*((K39/105-1)/2+1) -> 234.28571 | K39: 100 | L39: 990 | M39: 0.36 | N39: =D39*340 -> 680 | O39: =400*D39 -> 800 | P39: =IF(F39<10000,F39*0.3,IF(F39>49999.99,F39*0.1,(0.29-0.000003125*F39)*F39)) -> 442.2
A40: 4 | B40: 塑壳断路器 | C40: XT3N250 TMD 250 3P FF | D40: 2 | E40: =ROUND(H40,0) -> 1056 | F40: =E40*D40 -> 2112 | G40: =VLOOKUP(C40,库!A:D,4,FALSE()) -> ABB | H40: =VLOOKUP(C40,库!A:D,3,FALSE()) -> 1055.538 | I40: =D40*250 -> 500 | J40: =192*D40*((K39/105-1)/2+1) -> 374.85714 | L40: 1160 | M40: 0.48 | N40: =D40*192 -> 384 | O40: =400*D40 -> 800 | P40: =IF(F40<10000,F40*0.3,IF(F40>49999.99,F40*0.1,(0.29-0.000003125*F40)*F40)) -> 633.6
A41: 5 | B41: 塑壳断路器 | C41: XT5N400 TMA 400 3P FF | D41: 0 | E41: =ROUND(H41,0) -> 1579 | F41: =E41*D41 -> 0 | G41: =VLOOKUP(C41,库!A:D,4,FALSE()) -> ABB | H41: =VLOOKUP(C41,库!A:D,3,FALSE()) -> 1578.726 | I41: =D41*400 -> 0 | J41: =192*D41*((K39/105-1)/2+1) -> 0 | L41: 1500 | M41: 0.6 | N41: =D41*192 -> 0 | O41: =400*D41 -> 0 | P41: =IF(F41<10000,F41*0.3,IF(F41>49999.99,F41*0.1,(0.29-0.000003125*F41)*F41)) -> 0
A42: 6 | B42: 塑壳断路器 | C42: XT5N630 TMA 500 3P FF | D42: 0 | E42: =ROUND(H42,0) -> 2960 | F42: =E42*D42 -> 0 | G42: =VLOOKUP(C42,库!A:D,4,FALSE()) -> ABB | H42: =VLOOKUP(C42,库!A:D,3,FALSE()) -> 2960.451 | I42: =D42*500 -> 0 | J42: =401*D42*((K39/105-1)/2+1) -> 0 | M42: 0.72 | N42: =D42*192 -> 0 | O42: =400*D42 -> 0 | P42: =IF(F42<10000,F42*0.3,IF(F42>49999.99,F42*0.1,(0.29-0.000003125*F42)*F42)) -> 0
A43: 7 | B43: 塑壳断路器 | C43: XT5N630 TMA 630 3P FF | D43: 0 | E43: =ROUND(H43,0) -> 3746 | F43: =E43*D43 -> 0 | G43: =VLOOKUP(C43,库!A:D,4,FALSE()) -> ABB | H43: =VLOOKUP(C43,库!A:D,3,FALSE()) -> 3745.7505 | I43: =630*D43 -> 0 | J43: =401*D43*((K39/105-1)/2+1) -> 0 | N43: =D43*192 -> 0 | O43: =400*D43 -> 0 | P43: =IF(F43<10000,F43*0.3,IF(F43>49999.99,F43*0.1,(0.29-0.000003125*F43)*F43)) -> 0
A44: 8 | B44: 框架断路器 | C44: E1C630 T LSI 3P WHR | D44: 0 | E44: =ROUND(H44,0) -> 16613 | F44: =E44*D44 -> 0 | G44: =VLOOKUP(C44,库!A:D,4,FALSE()) -> ABB | H44: =VLOOKUP(C44,库!A:D,3,FALSE()) -> 16612.992 | I44: =630*D44 -> 0 | J44: =2.5*D44*0.25*K39*8.9*3 -> 0 | N44: =D44*192 -> 0 | O44: =400*D44 -> 0 | P44: =IF(F44<10000,F44*0.3,IF(F44>49999.99,F44*0.1,(0.29-0.000003125*F44)*F44)) -> 0
A45: 9 | B45: 框架断路器 | C45: E1C800 T LSI 3P WHR | D45: 1 | E45: =ROUND(H45,0) -> 17661 | F45: =E45*D45 -> 17661 | G45: =VLOOKUP(C45,库!A:D,4,FALSE()) -> ABB | H45: =VLOOKUP(C45,库!A:D,3,FALSE()) -> 17660.923 | I45: =800*D45 -> 800 | J45: =2.5*D45*0.3*K39*8.9*3 -> 2002.5 | N45: =D45*192 -> 192 | O45: =400*D45 -> 400 | P45: =IF(F45<10000,F45*0.3,IF(F45>49999.99,F45*0.1,(0.29-0.000003125*F45)*F45)) -> 4146.9684
A46: 10 | B46: 框架断路器 | C46: E1C1000 T LSI 3P WHR | D46: 0 | E46: =ROUND(H46,0) -> 18988 | F46: =E46*D46 -> 0 | G46: =VLOOKUP(C46,库!A:D,4,FALSE()) -> ABB | H46: =VLOOKUP(C46,库!A:D,3,FALSE()) -> 18988.431 | I46: =1000*D46 -> 0 | J46: =2.5*D46*0.48*K39*8.9*3 -> 0 | N46: =D46*192 -> 0 | O46: =400*D46 -> 0 | P46: =IF(F46<10000,F46*0.3,IF(F46>49999.99,F46*0.1,(0.29-0.000003125*F46)*F46)) -> 0
A47: 11 | B47: 电流互感器 | C47: SDH-0.66 600/5及以下 | D47: =SUM(D37:D44)*3 -> 15 | E47: =ROUND(H47,0) -> 28 | F47: =E47*D47 -> 420 | G47: =VLOOKUP(C47,库!A:D,4,FALSE()) -> 宁波/天灵 | H47: =VLOOKUP(C47,库!A:D,3,FALSE()) -> 28 | P47: =IF(F47<10000,F47*0.3,IF(F47>49999.99,F47*0.1,(0.29-0.000003125*F47)*F47)) -> 126
A48: 12 | B48: 电流互感器 | C48: SDH-0.66 800/5 | D48: =D45*3 -> 3 | E48: =ROUND(H48,0) -> 45 | F48: =E48*D48 -> 135 | G48: =VLOOKUP(C48,库!A:D,4,FALSE()) -> 宁波/天灵 | H48: =VLOOKUP(C48,库!A:D,3,FALSE()) -> 45 | P48: =IF(F48<10000,F48*0.3,IF(F48>49999.99,F48*0.1,(0.29-0.000003125*F48)*F48)) -> 40.5
A49: 13 | B49: 电流互感器 | C49: SDH-0.66 1000/5 | D49: =D46*3 -> 0 | E49: =ROUND(H49,0) -> 65 | F49: =E49*D49 -> 0 | G49: =VLOOKUP(C49,库!A:D,4,FALSE()) -> 宁波/天灵 | H49: =VLOOKUP(C49,库!A:D,3,FALSE()) -> 65 | P49: =IF(F49<10000,F49*0.3,IF(F49>49999.99,F49*0.1,(0.29-0.000003125*F49)*F49)) -> 0
A50: 14 | B50: 数显仪表 | C50: MC7200 | D50: =SUM(D47:D49)/3 -> 6 | E50: =ROUND(H50,0) -> 280 | F50: =E50*D50 -> 1680 | G50: =VLOOKUP(C50,库!A:D,4,FALSE()) -> 宁波/美格 | H50: =VLOOKUP(C50,库!A:D,3,FALSE()) -> 280 | I50: =SUM(I37:I49) -> 1720 | J50: =K37*4*K39*8.9+K37*0.8*K39*8.9 -> 3417.6 | N50: =0.6*4*105*8.9+0.6*0.8*105*8.9 -> 2691.36 | P50: =IF(F50<10000,F50*0.3,IF(F50>49999.99,F50*0.1,(0.29-0.000003125*F50)*F50)) -> 504
A51: 15 | B51: 铜排 | C51: TMY-4*(100*10)+(100*8) | F51: =ROUND(H51,0) -> 10685 | G51: =VLOOKUP(B51,库!A:D,4,FALSE()) -> 江西/金来 | H51: =ROUND((7)*L51*K39*8.9+2*L51/2*K39*8.9+2*L51/4*K39*8.9+J51,0) -> 10685 | I51: =IF(D50>9,I50*0.7,IF(I50>5,I50*0.8)) -> 1376 | J51: =SUM(J37:J50) -> 6146.3857 | L51: =IF(I51<500.1,M37,(IF(I51<755.1,M38,IF(I51<990.1,M39,IF(I51<1160.1,M40,IF(I51<1500,M41,M42)))))) -> 0.6 | N51: =SUM(N37:N50) -> 4113.36 | O51: =SUM(O37:O50) -> 2400 | P51: =IF(F51<10000,F51*0.3,IF(F51>49999.99,F51*0.1,(0.29-0.000003125*F51)*F51)) -> 2741.8712
A52: 16 | B52: =Q52 -> 辅助材料（出线柜，6路出线） | F52: =ROUND(H52*1,) -> 650 | G52: =VLOOKUP(B52,库!A:D,4,FALSE()) -> 湖北/恒晟 | H52: =VLOOKUP(B52,库!A:D,3,FALSE()) -> 650 | O52: =63*2+100+250*2+400*3 -> 1926 | P52: =IF(F52<10000,F52*0.3,IF(F52>49999.99,F52*0.1,(0.29-0.000003125*F52)*F52)) -> 195 | Q52: =_xlfn.CONCAT(R52,S52,T52) -> 辅助材料（出线柜，6路出线） | R52: 辅助材料（出线柜， | S52: =D50 -> 6 | T52: 路出线）
A53: 17 | B53: 成套费（组装费、企业管理费、税收、利润等） | G53: =VLOOKUP(B53,库!A:D,4,FALSE()) -> 宁波/海越 | I53: =I51/I50 -> 0.8 | O53: =O52*0.7 -> 1348.2 | P53: =SUM(P37:P52) -> 8963.3395
A54: 18 | B54: =Q54 -> 箱体:GCS(出线抽屉柜、6路) | F54: =ROUND(H54,0) -> 4600 | G54: =VLOOKUP(B54,库!A:D,4,FALSE()) -> 宁波/海越 | H54: =2200+O51 -> 4600 | Q54: =_xlfn.CONCAT(R54,S54,T54) -> 箱体:GCS(出线抽屉柜、6路) | R54: 箱体:GCS(出线抽屉柜、 | S54: =D50 -> 6 | T54: 路)
A55: 19 | B55: 合计 | F55: =SUM(F37:F54) -> 39861 | H55: =SUM(F54,F37:F52) -> 39861
A57: =B30 -> 0
A58: 序号 | B58: 名 称 | C58: 型 号 | D58: 数量(只) | E58: 单价(元) | F58: 金额(元) | G58: 产地/品牌 | I58: 电流 | J58: 总电缆费用 | K58: 柜宽 | L58: 电流 | M58: 铜排规格
A59: 1 | B59: 塑壳断路器 | C59: XT1N160 TMD 63 3P FF | D59: 2 | E59: =ROUND(H59,0) -> 444 | F59: =E59*D59 -> 888 | G59: =VLOOKUP(C59,库!A:D,4,FALSE()) -> ABB | H59: =VLOOKUP(C59,库!A:D,3,FALSE()) -> 443.754 | I59: =63*D59 -> 126 | J59: =80*D59*((K61/105-1)/2+1) -> 156.19048 | K59: 0.6 | L59: 500 | M59: 0.18 | N59: =D59*166 -> 332 | O59: =400*D59 -> 800 | P59: =IF(F59<10000,F59*0.3,IF(F59>49999.99,F59*0.1,(0.29-0.000003125*F59)*F59)) -> 266.4
A60: 2 | B60: 塑壳断路器 | C60: XT1N160 TMD 100 3P FF | D60: 0 | E60: =ROUND(H60,0) -> 444 | F60: =E60*D60 -> 0 | G60: =VLOOKUP(C60,库!A:D,4,FALSE()) -> ABB | H60: =VLOOKUP(C60,库!A:D,3,FALSE()) -> 443.754 | I60: =100*D60 -> 0 | J60: =120*D60*((K61/105-1)/2+1) -> 0 | K60: 铜价 | L60: 755 | M60: 0.24 | N60: =D60*166 -> 0 | O60: =400*D60 -> 0 | P60: =IF(F60<10000,F60*0.3,IF(F60>49999.99,F60*0.1,(0.29-0.000003125*F60)*F60)) -> 0
A61: 3 | B61: 塑壳断路器 | C61: XT1N160 TMD 160 3P FF | D61: 3 | E61: =ROUND(H61,0) -> 737 | F61: =E61*D61 -> 2211 | G61: =VLOOKUP(C61,库!A:D,4,FALSE()) -> ABB | H61: =VLOOKUP(C61,库!A:D,3,FALSE()) -> 736.794 | I61: =160*D61 -> 480 | J61: =120*D61*((K61/105-1)/2+1) -> 351.42857 | K61: 100 | L61: 990 | M61: 0.36 | N61: =D61*340 -> 1020 | O61: =400*D61 -> 1200 | P61: =IF(F61<10000,F61*0.3,IF(F61>49999.99,F61*0.1,(0.29-0.000003125*F61)*F61)) -> 663.3
A62: 4 | B62: 塑壳断路器 | C62: XT3N250 TMD 250 3P FF | D62: 4 | E62: =ROUND(H62,0) -> 1056 | F62: =E62*D62 -> 4224 | G62: =VLOOKUP(C62,库!A:D,4,FALSE()) -> ABB | H62: =VLOOKUP(C62,库!A:D,3,FALSE()) -> 1055.538 | I62: =D62*250 -> 1000 | J62: =192*D62*((K61/105-1)/2+1) -> 749.71429 | L62: 1160 | M62: 0.48 | N62: =D62*192 -> 768 | O62: =400*D62 -> 1600 | P62: =IF(F62<10000,F62*0.3,IF(F62>49999.99,F62*0.1,(0.29-0.000003125*F62)*F62)) -> 1267.2
A63: 5 | B63: 塑壳断路器 | C63: XT5N400 TMA 400 3P FF | D63: 1 | E63: =ROUND(H63,0) -> 1579 | F63: =E63*D63 -> 1579 | G63: =VLOOKUP(C63,库!A:D,4,FALSE()) -> ABB | H63: =VLOOKUP(C63,库!A:D,3,FALSE()) -> 1578.726 | I63: =D63*400 -> 400 | J63: =192*D63*((K61/105-1)/2+1) -> 187.42857 | L63: 1500 | M63: 0.6 | N63: =D63*192 -> 192 | O63: =400*D63 -> 400 | P63: =IF(F63<10000,F63*0.3,IF(F63>49999.99,F63*0.1,(0.29-0.000003125*F63)*F63)) -> 473.7
A64: 6 | B64: 塑壳断路器 | C64: XT5N630 TMA 500 3P FF | D64: 0 | E64: =ROUND(H64,0) -> 2960 | F64: =E64*D64 -> 0 | G64: =VLOOKUP(C64,库!A:D,4,FALSE()) -> ABB | H64: =VLOOKUP(C64,库!A:D,3,FALSE()) -> 2960.451 | I64: =D64*500 -> 0 | J64: =401*D64*((K61/105-1)/2+1) -> 0 | M64: 0.72 | N64: =D64*192 -> 0 | O64: =400*D64 -> 0 | P64: =IF(F64<10000,F64*0.3,IF(F64>49999.99,F64*0.1,(0.29-0.000003125*F64)*F64)) -> 0
A65: 7 | B65: 塑壳断路器 | C65: XT5N630 TMA 630 3P FF | D65: 0 | E65: =ROUND(H65,0) -> 3746 | F65: =E65*D65 -> 0 | G65: =VLOOKUP(C65,库!A:D,4,FALSE()) -> ABB | H65: =VLOOKUP(C65,库!A:D,3,FALSE()) -> 3745.7505 | I65: =630*D65 -> 0 | J65: =401*D65*((K61/105-1)/2+1) -> 0 | N65: =D65*192 -> 0 | O65: =400*D65 -> 0 | P65: =IF(F65<10000,F65*0.3,IF(F65>49999.99,F65*0.1,(0.29-0.000003125*F65)*F65)) -> 0
A66: 8 | B66: 框架断路器 | C66: E1C630 T LSI 3P WHR | D66: 0 | E66: =ROUND(H66,0) -> 16613 | F66: =E66*D66 -> 0 | G66: =VLOOKUP(C66,库!A:D,4,FALSE()) -> ABB | H66: =VLOOKUP(C66,库!A:D,3,FALSE()) -> 16612.992 | I66: =630*D66 -> 0 | J66: =2.5*D66*0.25*K61*8.9*3 -> 0 | N66: =D66*192 -> 0 | O66: =400*D66 -> 0 | P66: =IF(F66<10000,F66*0.3,IF(F66>49999.99,F66*0.1,(0.29-0.000003125*F66)*F66)) -> 0
A67: 9 | B67: 框架断路器 | C67: E1C800 T LSI 3P WHR | D67: 0 | E67: =ROUND(H67,0) -> 17661 | F67: =E67*D67 -> 0 | G67: =VLOOKUP(C67,库!A:D,4,FALSE()) -> ABB | H67: =VLOOKUP(C67,库!A:D,3,FALSE()) -> 17660.923 | I67: =800*D67 -> 0 | J67: =2.5*D67*0.3*K61*8.9*3 -> 0 | N67: =D67*192 -> 0 | O67: =400*D67 -> 0 | P67: =IF(F67<10000,F67*0.3,IF(F67>49999.99,F67*0.1,(0.29-0.000003125*F67)*F67)) -> 0
A68: 10 | B68: 框架断路器 | C68: E1C1000 T LSI 3P WHR | D68: 1 | E68: =ROUND(H68,0) -> 18988 | F68: =E68*D68 -> 18988 | G68: =VLOOKUP(C68,库!A:D,4,FALSE()) -> ABB | H68: =VLOOKUP(C68,库!A:D,3,FALSE()) -> 18988.431 | I68: =1000*D68 -> 1000 | J68: =2.5*D68*0.48*K61*8.9*3 -> 3204 | N68: =D68*192 -> 192 | O68: =400*D68 -> 400 | P68: =IF(F68<10000,F68*0.3,IF(F68>49999.99,F68*0.1,(0.29-0.000003125*F68)*F68)) -> 4379.8196
A69: 11 | B69: 电流互感器 | C69: SDH-0.66 600/5及以下 | D69: =SUM(D59:D66)*3 -> 30 | E69: =ROUND(H69,0) -> 28 | F69: =E69*D69 -> 840 | G69: =VLOOKUP(C69,库!A:D,4,FALSE()) -> 宁波/天灵 | H69: =VLOOKUP(C69,库!A:D,3,FALSE()) -> 28 | P69: =IF(F69<10000,F69*0.3,IF(F69>49999.99,F69*0.1,(0.29-0.000003125*F69)*F69)) -> 252
A70: 12 | B70: 电流互感器 | C70: SDH-0.66 800/5 | D70: =D67*3 -> 0 | E70: =ROUND(H70,0) -> 45 | F70: =E70*D70 -> 0 | G70: =VLOOKUP(C70,库!A:D,4,FALSE()) -> 宁波/天灵 | H70: =VLOOKUP(C70,库!A:D,3,FALSE()) -> 45 | P70: =IF(F70<10000,F70*0.3,IF(F70>49999.99,F70*0.1,(0.29-0.000003125*F70)*F70)) -> 0
A71: 13 | B71: 电流互感器 | C71: SDH-0.66 1000/5 | D71: =D68*3 -> 3 | E71: =ROUND(H71,0) -> 65 | F71: =E71*D71 -> 195 | G71: =VLOOKUP(C71,库!A:D,4,FALSE()) -> 宁波/天灵 | H71: =VLOOKUP(C71,库!A:D,3,FALSE()) -> 65 | P71: =IF(F71<10000,F71*0.3,IF(F71>49999.99,F71*0.1,(0.29-0.000003125*F71)*F71)) -> 58.5
A72: 14 | B72: 数显仪表 | C72: MC7200 | D72: =SUM(D69:D71)/3 -> 11 | E72: =ROUND(H72,0) -> 280 | F72: =E72*D72 -> 3080 | G72: =VLOOKUP(C72,库!A:D,4,FALSE()) -> 宁波/美格 | H72: =VLOOKUP(C72,库!A:D,3,FALSE()) -> 280 | I72: =SUM(I59:I71) -> 3006 | J72: =K59*4*K61*8.9+K59*0.8*K61*8.9 -> 2563.2 | N72: =0.6*4*105*8.9+0.6*0.8*105*8.9 -> 2691.36 | P72: =IF(F72<10000,F72*0.3,IF(F72>49999.99,F72*0.1,(0.29-0.000003125*F72)*F72)) -> 924
A73: 15 | B73: 铜排 | C73: TMY-4*(100*10)+(100*8) | F73: =ROUND(H73,0) -> 12659 | G73: =VLOOKUP(B73,库!A:D,4,FALSE()) -> 江西/金来 | H73: =ROUND((7)*L73*K61*8.9+2*L73/2*K61*8.9+2*L73/4*K61*8.9+J73,0) -> 12659 | I73: =IF(D72>9,I72*0.7,IF(I72>5,I72*0.8)) -> 2104.2 | J73: =SUM(J59:J72) -> 7211.9619 | L73: =IF(I73<500.1,M59,(IF(I73<755.1,M60,IF(I73<990.1,M61,IF(I73<1160.1,M62,IF(I73<1500,M63,M64)))))) -> 0.72 | N73: =SUM(N59:N72) -> 5195.36 | O73: =SUM(O59:O72) -> 4400 | P73: =IF(F73<10000,F73*0.3,IF(F73>49999.99,F73*0.1,(0.29-0.000003125*F73)*F73)) -> 3170.3279
A74: 16 | B74: =Q74 -> 辅助材料（出线柜，11路出线） | F74: =ROUND(H74*1,) -> 900 | G74: =VLOOKUP(B74,库!A:D,4,FALSE()) -> 湖北/恒晟 | H74: =VLOOKUP(B74,库!A:D,3,FALSE()) -> 900 | O74: =63*2+100+250*2+400*3 -> 1926 | P74: =IF(F74<10000,F74*0.3,IF(F74>49999.99,F74*0.1,(0.29-0.000003125*F74)*F74)) -> 270 | Q74: =_xlfn.CONCAT(R74,S74,T74) -> 辅助材料（出线柜，11路出线） | R74: 辅助材料（出线柜， | S74: =D72 -> 11 | T74: 路出线）
A75: 17 | B75: 成套费（组装费、企业管理费、税收、利润等） | G75: =VLOOKUP(B75,库!A:D,4,FALSE()) -> 宁波/海越 | I75: =I73/I72 -> 0.7 | O75: =O74*0.7 -> 1348.2 | P75: =SUM(P59:P74) -> 11725.247
A76: 18 | B76: =Q76 -> 箱体:GCS(出线抽屉柜、11路) | F76: =ROUND(H76,0) -> 6600 | G76: =VLOOKUP(B76,库!A:D,4,FALSE()) -> 宁波/海越 | H76: =2200+O73 -> 6600 | Q76: =_xlfn.CONCAT(R76,S76,T76) -> 箱体:GCS(出线抽屉柜、11路) | R76: 箱体:GCS(出线抽屉柜、 | S76: =D72 -> 11 | T76: 路)
A77: 19 | B77: 合计 | F77: =SUM(F59:F76) -> 52164 | H77: =SUM(F76,F59:F74) -> 52164
A89: =A26 -> 报价日期：2026年1月28日 有效期：30天 报价：洪辉 审核:袁剑幸

Sheet 库
A1: 型号 | B1: 名称 | C1: 单价 | D1: 产地/厂家 | E1: 面价 | F1: 附件 | G1: 折扣 | H1: 板前 | I1: 分励 | J1: 辅助 | K1: 报警 | L1: 电动机保护 | M1: 插入式板后
A2: 2*Mkk480-D-01/B44066D7050 | B2: 电容电抗 | C2: 11500 | D2: 爱普科斯
A3: SJ2206HA2BAL | B3: 风机 | C3: 220 | D3: 台湾/三巨
A4: 3AE-EP 12KV-630A-31.5KA 手车式 | B4: 真空断路器 | C4: 35764 | D4: 西门子
A5: 3AJ1-12 630A-25手车式 | B5: 真空断路器 | C5: 27800 | D5: 西门子
A6: 3AS4-12 1250-31.5手车式 | B6: 真空断路器 | C6: 28000 | D6: 伊顿
A7: 3AS4-12 630-25手车式 | B7: 真空断路器 | C7: 26000 | D7: 伊顿
A9: 3VL400N400 TM PB/3340 螺钉端子 | B9: 塑壳断路器 | C9: =5678*0.7*0.95 -> 3775.87 | D9: 西门子 | E9: =7099*0.58 -> 4117.42
A10: 3VL630H630 TM PB/3340 螺钉端子 | B10: 塑壳断路器 | C10: =9064*0.7*0.95 -> 6027.56 | D10: 西门子 | E10: =10963*0.58 -> 6358.54
A11: 3VL630H630 TM PB/3P 螺钉端子 | B11: 塑壳断路器 | C11: =8489*0.7*0.95 -> 5645.185 | D11: 西门子 | E11: =10368*0.58 -> 6013.44
A12: 3WL1N08 ETU45B 抽屉电动 | B12: 框架断路器 | C12: =45092*0.6*0.95 -> 25702.44 | D12: 西门子 | E12: =48424*0.54 -> 26148.96
A13: 3WL1N10 ETU45B 抽屉电动 | B13: 框架断路器 | C13: =48000*0.6*0.95 -> 27360 | D13: 西门子 | E13: =51452*0.54 -> 27784.08
A14: 3WL1N12 ETU45B 抽屉电动 | B14: 框架断路器 | C14: =50043*0.6*0.95 -> 28524.51 | D14: 西门子 | E14: =53578*0.54 -> 28932.12
A15: 3WL2N20 ETU45B 抽屉电动 | B15: 框架断路器 | C15: =63837*0.6*0.95 -> 36387.09 | D15: 西门子 | E15: =69855*0.54 -> 37721.7
A16: 42L6-A | B16: 电流表 | C16: 21 | D16: 宁波/电子
A17: 42L6-COS | B17: 功率因数表 | C17: 65 | D17: 宁波/电子
A18: 42L6-V | B18: 电压表 | C18: 21 | D18: 宁波/电子
A19: 42L6-V 10/0.1KV | B19: 电压表 | C19: 21 | D19: 宁波/电子
A20: 42L6-W | B20: 功率表 | C20: 80 | D20: 宁波/电子
A21: 6L2-A | B21: 电流表 | C21: 17 | D21: 宁波/电子
A22: 6L2-COS | B22: 功率因素表 | C22: 65 | D22: 宁波/电子
A23: 6L2-V | B23: 电压表 | C23: 17 | D23: 宁波/电子
A24: 6L2-W | B24: 功率表 | C24: 80 | D24: 宁波/电子
A25: 99T1-A | B25: 电流表 | C25: 17 | D25: 宁波/电子
A26: A1-270# | B26: 计量表架 | C26: 23 | D26: 海盐/同安 | G26: =2060*0.65 -> 1339
A27: A-APF/4L-100A C | B27: 有源滤波器 | C27: 158000 | D27: 南京/亚派
A28: A-APF/4L-150A C | B28: 有源滤波器 | C28: 237000 | D28: 南京/亚派
A29: ACR120EL | B29: 数显仪表 | C29: =2000*0.65 -> 1300 | D29: 上海/安科瑞
A30: ACR210EL | B30: 数显仪表 | C30: =1400*0.65 -> 910 | D30: 上海/安科瑞
A31: ACR220EL | B31: 数显仪表 | C31: =2000*0.65 -> 1300 | D31: 上海/安科瑞
A32: ACR220ELH | B32: 数显仪表 | C32: =3200*0.65 -> 2080 | D32: 上海/安科瑞
A33: ACR230ELH | B33: 数显仪表 | C33: =3600*0.65 -> 2340 | D33: 上海/安科瑞
A34: ACR330ELH | B34: 数显仪表 | C34: =3600*0.65 -> 2340 | D34: 上海/安科瑞
A35: Acuvim387 | B35: 数显仪表 | C35: 1600 | D35: 北京/爱博
A36: Acuvim-390 | B36: 数显仪表 | C36: 2200 | D36: 北京/爱博
A37: Acuvim-CL | B37: 数显仪表 | C37: 2640 | D37: 北京/爱博
A38: AcuvimII | B38: 数显仪表 | C38: 3200 | D38: 北京/爱博
A40: AL2D 480V 100KVAR+XKIB 74/400/6-50 | B40: 电容器 | C40: 11815 | D40: 芬兰/诺基亚
A41: AL2D 480V 50KVAR+XKIB 37/400/6-50 | B41: 电容器 | C41: 8550 | D41: 芬兰/诺基亚
A42: ALP08 | B42: 电容器 | C42: 5138 | D42: 阿尔卑斯
A43: ALP12 | B43: 电容器 | C43: 5857 | D43: 阿尔卑斯
A44: AN-13D4-13A AG5抽屉电动失压 | B44: 框架断路器 | C44: =41675*0.67+882/3*0.67 -> 28119.23 | D44: LS产电
A45: AN-16D4-16A AG5抽屉电动失压 | B45: 框架断路器 | C45: =44762*0.67+882/3*0.67 -> 30187.52 | D45: LS产电
A46: ANJ-BCY8 | B46: 状态显示器 | C46: 800 | D46: 台州/安耐杰
A48: ANJ-GB/450-10.10 | B48: 智能电容器 | C48: 1300 | D48: 台州/安耐杰
A49: ANJ-GB/480(XL)-40-7% | B49: 电容电抗器 | C49: 5100 | D49: 台州/安耐杰
A50: ANJ-GB/480-40-7% | B50: 智能电容器 | C50: 5500 | D50: 台州/安耐杰
A51: APK440-3-45 | B51: 电容器 | C51: 1656 | D51: 美国/电能设备
A52: ARC PROTECTION VAMP 120 | B52: 弧光报警装置 | D52: 芬兰/诺基亚
A53: ATNSX-250F/4P | B53: 双电源转换开关 | C53: =22855*0.65 -> 14855.75 | D53: 施耐德
A54: ATNSX-400F/4P | B54: 双电源转换开关 | C54: =32902*0.65 -> 21386.3 | D54: 施耐德
A55: B105 | B55: 接触器 | C55: =700*0.7 -> 490 | D55: 上海/人民
A56: B16 | B56: 接触器 | C56: =52*0.7 -> 36.4 | D56: 上海/人民
A57: B170 | B57: 接触器 | C57: =900*0.7 -> 630 | D57: 上海/人民
A58: B25 | B58: 接触器 | C58: =75*0.7 -> 52.5 | D58: 上海/人民
A59: B250 | B59: 接触器 | C59: =2200*0.7 -> 1540 | D59: 上海/人民
A60: B25C | B60: 接触器 | C60: =115*0.75 -> 86.25 | D60: 上海/人民
A61: B30 | B61: 接触器 | C61: =95*0.7 -> 66.5 | D61: 上海/人民
A62: B30C | B62: 接触器 | C62: =122*0.7 -> 85.4 | D62: 上海/人民
A63: B370 | B63: 接触器 | C63: =3000*0.7 -> 2100 | D63: 上海/人民
A64: B45 | B64: 接触器 | C64: =130*0.7 -> 91 | D64: 上海/人民
A65: B50C | B65: 接触器 | C65: =260*0.75 -> 195 | D65: 上海/人民
A66: B63C | B66: 接触器 | C66: =280*0.75 -> 210 | D66: 上海/人民
A68: B75C | B68: 接触器 | C68: =300*0.75 -> 225 | D68: 上海/人民
A70: BCMJ-0.25-15-3Y | B70: 电容器 | C70: =15*18 -> 270 | D70: 宁波/新容
A71: BCMJ-0.25-20-3Y | B71: 电容器 | C71: =20*18 -> 360 | D71: 宁波/新容
A72: BCMJ-0.25-6-3Y | B72: 电容器 | C72: =6*18 -> 108 | D72: 宁波/新容
A73: BCMJ0.415-35-3 | B73: 电容器 | C73: =35*10.8 -> 378 | D73: 宁波/新容
A74: BCMJ0.4-20-3 | B74: 电容器 | C74: =20*10.8 -> 216 | D74: 宁波/新容
A75: BCMJ0.4-25-3 | B75: 电容器 | C75: =25*10.8 -> 270 | D75: 宁波/新容
A76: BCMJ0.4-30-3 | B76: 电容器 | C76: =30*10.8 -> 324 | D76: 宁波/新容
A77: BCMJ0.4-40-3 | B77: 电容器 | C77: =40*10.8 -> 432 | D77: 宁波/新容
A78: BK-500VA | B78: 中间变压器 | C78: 500 | D78: 浙江/正泰
A79: BKMJ0.4-20-3 | B79: 电容器 | C79: =16*20 -> 320 | D79: 宁波/新容
A80: BKMJ0.4-40-3 | B80: 电容器 | C80: 640 | D80: 宁波/新容
A81: BKPF X12-T-3A | B81: 补偿控制器 | C81: =5600*0.9 -> 5040 | D81: 博鲁克
A82: BKPL-25-480-7S | B82: 电容电抗组合 | C82: =5400*0.9 -> 4860 | D82: 博鲁克
A83: BKPL-50-440-7S | B83: 电容电抗组合 | C83: =10550*0.9 -> 9495 | D83: 博鲁克
A84: BKTS | B84: 晶闸管开关 | C84: =4800*0.9 -> 4320 | D84: 博鲁克
A86: CB125N/25A/3P | B86: 塑壳断路器 | C86: 557.6 | D86: 美国/通用
A87: CB125N/50A/3P 插拔 | B87: 塑壳断路器 | C87: =557.6+576 -> 1133.6 | D87: 美国/通用
A88: CB125N/80A/3P 插拔 | B88: 塑壳断路器 | C88: =557.6+576 -> 1133.6 | D88: 美国/通用
A89: CB125N4TM100 | B89: 塑壳断路器 | C89: 785 | D89: 美国/通用 | F89: FEN-160/4P TM100A
A90: CB125S3TM100 插拔 | B90: 塑壳断路器 | C90: =469+612 -> 1081 | D90: 美国/通用 | F90: FDS160/3P TD100A 插拔
A91: CB125S3TM100分励 插拔 | B91: 塑壳断路器 | C91: =469+612+147.2 -> 1228.2 | D91: 美国/通用 | F91: FDS160/3P TD100A分励 插拔
A92: CB125S3TM125 插拔 | B92: 塑壳断路器 | C92: =608+612 -> 1220 | D92: 美国/通用 | F92: FDS160/3P TD125A 插拔
A93: CB125S3TM125A分励 插拔 | B93: 塑壳断路器 | C93: =608+612+147.2 -> 1367.2 | D93: 美国/通用 | F93: FDS160/3P TD125A分励 插拔
A94: CB125S3TM63 | B94: 塑壳断路器 | C94: 469.6 | D94: 美国/通用
A95: CB125S3TM80 | B95: 塑壳断路器 | C95: 469.6 | D95: 美国/通用
A96: CB250N/160A/3P 插拔 | B96: 塑壳断路器 | C96: =805.6+992 -> 1797.6 | D96: 美国/通用
A97: CB250N/200A/3P 插拔 | B97: 塑壳断路器 | C97: =1360.8+992 -> 2352.8 | D97: 美国/通用
A98: CB250N/250A/3P 插拔 | B98: 塑壳断路器 | C98: =1360.8+992 -> 2352.8 | D98: 美国/通用
A99: CB250S3TM125 | B99: 塑壳断路器 | C99: 728 | D99: 美国/通用
A100: CB250S3TM160 | B100: 塑壳断路器 | C100: 728 | D100: 美国/通用
A101: CB250S3TM160分励 插拔 | B101: 塑壳断路器 | C101: =728+1040.8+147.2 -> 1916 | D101: 美国/通用 | F101: FDS160/3P TM160A分励 插拔
A102: CB250S3TM200 | B102: 塑壳断路器 | C102: 1052 | D102: 美国/通用
A103: CB250S3TM250 | B103: 塑壳断路器 | C103: 1052 | D103: 美国/通用
A104: CB250S3TM250分励 插拔 | B104: 塑壳断路器 | C104: =1052+1040.8+147.2 -> 2240 | D104: 美国/通用 | F104: FEV250/3P TMD250A分励 插拔
A105: CB400N/400A/3P 插拔 | B105: 塑壳断路器 | C105: =2578.4+1472 -> 4050.4 | D105: 美国/通用
A106: CB400N3TM400分励 插拔 | B106: 塑壳断路器 | C106: =2578.4+1664.8+147.2 -> 4390.4 | D106: 美国/通用 | F106: FGN400/3P AA400分励 插拔
...
